brython_dev/__init__.py
brython_dev/__main__.py
brython_dev-0.13.1.dist-info/entry_points.txt
brython_dev-0.13.1.dist-info/LICENSE
brython_dev-0.13.1.dist-info/METADATA
brython_dev-0.13.1.dist-info/WHEEL
brython_dev-0.13.1.dist-info/RECORD
