Metadata-Version: 2.3
Name: brython-dev
Version: 0.13.1
Summary: Brython developer tools
License: MIT
Keywords: brython,Development,Build Tools,Debuggers,Testing
Author: Lorenzo Garcia Calzadilla
Author-email: lorenzogarciacalzadilla@gmail.com
Requires-Python: >=3.13,<4.0
Classifier: Development Status :: 3 - Alpha
Classifier: Intended Audience :: Developers
Classifier: License :: OSI Approved :: MIT License
Classifier: Programming Language :: Python
Classifier: Programming Language :: Python :: 3
Classifier: Programming Language :: Python :: 3.13
Classifier: Topic :: Software Development
Classifier: Topic :: Software Development :: Bug Tracking
Classifier: Topic :: Software Development :: Build Tools
Classifier: Topic :: Software Development :: Debuggers
Classifier: Topic :: Software Development :: Testing
Classifier: Topic :: Utilities
Requires-Dist: brython (>=3.13.1,<4.0.0)
Requires-Dist: flask (>=3.1.0,<4.0.0)
Requires-Dist: pyyaml (>=6.0.2,<7.0.0)
